preg2/glitch_struct.v
// glitch_struct.v
`timescale 1ns/1ps

module glitch_detector_struct (
  input  wire a,    // cambia en t₀ de 1→0
  input  wire b,
  input  wire c,
  input  wire d,
  output wire F     // resultado con glitch entre 7 ns y 9 ns
);
  // Wires internos
  wire a_n, b_n, c_n, d_n;
  wire or1, or2;
  wire and1, and2;

  // Inversores (retardo 1 ns)
  //   a_n sube en t₀+1 ns
  not #1 inv_a (a_n, a);
  not #1 inv_d (d_n, d);

  // OR2 = b' + c' (retardo 3 ns)
  //   or2 estable antes de t₀
  not #1 inv_b (b_n, b);
  not #1 inv_c (c_n, c);
  or  #3 or2_gate  (or2, b_n, c_n);

  // OR1 = a + b (retardo 3 ns)
  //   en t₀+3 ns or1 sigue la caída de 'a'
  or  #3 or1_gate  (or1, a, b);

  // AND1 = or1 · or2 (retardo 3 ns)
  //   en t₀+3+3 = 6 ns and1 cae a 0
  and #0 and1_gate (and1, or1, or2);

  // AND2 = a_n · d_n (retardo 3 ns)
  //   a_n sube en t₀+1 → and2 sube en t₀+1+3 = 4 ns
  and #3 and2_gate (and2, a_n, d_n);

  // F = and1 + and2 (retardo 3 ns)
  //   ruta backup llega en t₀+4+3 = 7 ns (F vuelve a 1)
  //   ruta main cae en   t₀+6+3 = 9 ns (F ya había caído en 9(ns))
  //   glitch en [7 ns .. 9 ns]
  or  #0 orF_gate  (F, and1, and2);
endmodule

preg2/tb_struct.v
`timescale 1ns/1ps
module tb_struct;
  reg  a, b, c, d;
  wire F;

  glitch_detector_struct uut (
    .a(a), .b(b), .c(c), .d(d),
    .F(F)
  );

  initial begin
    $dumpfile("glitch_struct.vcd");
    $dumpvars(0,tb_struct);
  end

  initial begin
    // --------- Caso 1: 1000 → 0000 ---------
    // t=0: a=1,b=0,c=0,d=0 ⇒ F=1
    a=1; b=0; c=0; d=0;
    #10;
    // t=10: solo a cambia → 0 ⇒ primer glitch
    a=0;
    #20;

    // --------- Caso 2: 1010 → 0010 ---------
    // t=30: a=1,b=0,c=1,d=0 ⇒ F=1
    a=1; b=0; c=1; d=0;
    #10;
    // t=40: solo a cambia → 0 ⇒ segundo glitch
    a=0;
    #20;

    $finish;
  end
endmodule

preg2/glitch_struct.vcd
$date
	Mon May 26 20:47:26 2025
$end
$version
	Icarus Verilog
$end
$timescale
	1ps
$end
$scope module tb_struct $end
$var wire 1 ! F $end
$var reg 1 " a $end
$var reg 1 # b $end
$var reg 1 $ c $end
$var reg 1 % d $end
$scope module uut $end
$var wire 1 ! F $end
$var wire 1 " a $end
$var wire 1 & a_n $end
$var wire 1 ' and1 $end
$var wire 1 ( and2 $end
$var wire 1 # b $end
$var wire 1 ) b_n $end
$var wire 1 $ c $end
$var wire 1 * c_n $end
$var wire 1 % d $end
$var wire 1 + d_n $end
$var wire 1 , or1 $end
$var wire 1 - or2 $end
$upscope $end
$upscope $end
$enddefinitions $end
$comment Show the parameter values. $end
$dumpall
$end
#0
$dumpvars
x-
x,
x+
x*
x)
x(
x'
x&
0%
0$
0#
1"
x!
$end
#1000
1+
1*
1)
0&
#3000
1,
#4000
1!
1'
1-
0(
#10000
0"
#11000
1&
#13000
0!
0'
0,
#14000
1!
1(
#30000
1$
1"
#31000
0*
0&
#33000
1'
1,
#34000
0(
#40000
0"
#41000
1&
#43000
0!
0'
0,
#44000
1!
1(
